d_flipflop/dflipflop.sv
module dflipflop(
    input logic d,
    input logic clk,
    input logic reset,
    output logic q
);
always @(posedge clk or posedge reset)
begin 
    if (reset) begin
        q<=1'b0;
    end
    else
        q<=d;
end
endmodule

d_flipflop/tb.sv
`timescale 1ns/1ps

module tb;

logic d;
logic reset;
logic clk;
logic q;

dflipflop dut(
    .d(d),
    .reset(reset),
    .clk(clk),
    .q(q)
);
initial begin
    clk = 0;
    forever #5 clk = ~clk;
end
initial begin
    $monitor("t=%0t clk=%b reset=%b d=%b q=%b",
              $time, clk, reset, d, q);
end

initial begin
    $dumpfile("wave.vcd");
    $dumpvars(0, tb);
end

// Stimulus
initial begin

    reset = 1;
    d = 0;

    #12;
    reset = 0;     

    d = 1;          
    #10;

    d = 0;        
    #10;

    d = 1;          
    #10;
    reset = 1;     
    #10;

    reset = 0;
    d = 1;
    #10;

    $finish;
end

endmodule

d_flipflop/wave.vcd
$date
	Sat Jun 20 20:58:06 2026
$end
$version
	Icarus Verilog
$end
$timescale
	1ps
$end
$scope module tb $end
$var wire 1 ! q $end
$var reg 1 " clk $end
$var reg 1 # d $end
$var reg 1 $ reset $end
$scope module dut $end
$var wire 1 " clk $end
$var wire 1 # d $end
$var wire 1 $ reset $end
$var reg 1 ! q $end
$upscope $end
$upscope $end
$enddefinitions $end
$comment Show the parameter values. $end
$dumpall
$end
#0
$dumpvars
1$
0#
0"
0!
$end
#5000
1"
#10000
0"
#12000
1#
0$
#15000
1!
1"
#20000
0"
#22000
0#
#25000
0!
1"
#30000
0"
#32000
1#
#35000
1!
1"
#40000
0"
#42000
0!
1$
#45000
1"
#50000
0"
#52000
0$
#55000
1!
1"
