4bit_up_down_counter/counter.sv
module up_down_counter_4(
    input logic clk,
    input logic reset,
    input logic up,
    output logic [3:0]count
);
always_ff@(posedge clk)begin
    if (reset)
        count<=4'b0000;
    else if (up)
        count<=count+1;
    else 
    count<=count-1;
end
endmodule

4bit_up_down_counter/tb.sv
module tb;
logic clk;
logic reset;
logic up;
logic [3:0]count;

up_down_counter_4 dut(
    .clk(clk),
    .reset(reset),
    .up(up),
    .count(count)
);
initial begin 
    clk=0;
    forever #5 clk=~clk;
end
initial begin 
    $dumpfile("waves.vcd");
    $dumpvars(0,tb);
    $monitor("time=%0t reset=%b up_down=%b count=%b",
    $time,reset,up,count);

    reset=1;
    #10;
    reset=0;
    up=1;
    #200;
    reset=1;
    #10;
    reset=0;
    up=0;
    #200;
    $finish;
end
endmodule

4bit_up_down_counter/waves.vcd
$date
	Mon Jun 22 20:55:03 2026
$end
$version
	Icarus Verilog
$end
$timescale
	1s
$end
$scope module tb $end
$var wire 4 ! count [3:0] $end
$var reg 1 " clk $end
$var reg 1 # reset $end
$var reg 1 $ up $end
$scope module dut $end
$var wire 1 " clk $end
$var wire 1 # reset $end
$var wire 1 $ up $end
$var reg 4 % count [3:0] $end
$upscope $end
$upscope $end
$enddefinitions $end
$comment Show the parameter values. $end
$dumpall
$end
#0
$dumpvars
bx %
x$
1#
0"
bx !
$end
#5
b0 !
b0 %
1"
#10
0"
1$
0#
#15
b1 !
b1 %
1"
#20
0"
#25
b10 !
b10 %
1"
#30
0"
#35
b11 !
b11 %
1"
#40
0"
#45
b100 !
b100 %
1"
#50
0"
#55
b101 !
b101 %
1"
#60
0"
#65
b110 !
b110 %
1"
#70
0"
#75
b111 !
b111 %
1"
#80
0"
#85
b1000 !
b1000 %
1"
#90
0"
#95
b1001 !
b1001 %
1"
#100
0"
#105
b1010 !
b1010 %
1"
#110
0"
#115
b1011 !
b1011 %
1"
#120
0"
#125
b1100 !
b1100 %
1"
#130
0"
#135
b1101 !
b1101 %
1"
#140
0"
#145
b1110 !
b1110 %
1"
#150
0"
#155
b1111 !
b1111 %
1"
#160
0"
#165
b0 !
b0 %
1"
#170
0"
#175
b1 !
b1 %
1"
#180
0"
#185
b10 !
b10 %
1"
#190
0"
#195
b11 !
b11 %
1"
#200
0"
#205
b100 !
b100 %
1"
#210
0"
1#
#215
b0 !
b0 %
1"
#220
0"
0$
0#
#225
b1111 !
b1111 %
1"
#230
0"
#235
b1110 !
b1110 %
1"
#240
0"
#245
b1101 !
b1101 %
1"
#250
0"
#255
b1100 !
b1100 %
1"
#260
0"
#265
b1011 !
b1011 %
1"
#270
0"
#275
b1010 !
b1010 %
1"
#280
0"
#285
b1001 !
b1001 %
1"
#290
0"
#295
b1000 !
b1000 %
1"
#300
0"
#305
b111 !
b111 %
1"
#310
0"
#315
b110 !
b110 %
1"
#320
0"
#325
b101 !
b101 %
1"
#330
0"
#335
b100 !
b100 %
1"
#340
0"
#345
b11 !
b11 %
1"
#350
0"
#355
b10 !
b10 %
1"
#360
0"
#365
b1 !
b1 %
1"
#370
0"
#375
b0 !
b0 %
1"
#380
0"
#385
b1111 !
b1111 %
1"
#390
0"
#395
b1110 !
b1110 %
1"
#400
0"
#405
b1101 !
b1101 %
1"
#410
0"
#415
b1100 !
b1100 %
1"
