mod_10_counter/counter.sv
module mod10counter(
    input logic clk,
    input logic reset,
    output logic[3:0]count
);
always_ff @(posedge clk ) begin 
    if (reset)
        count<=4'b0000;
    else if (count==9)
        count<=4'b0000;
    else
        count<=count+1;
end
endmodule

mod_10_counter/tb.sv
module tb;
logic reset;
logic clk;
logic [3:0]count;

mod10counter dut(
    .reset(reset),
    .clk(clk),
    .count(count)
);
initial begin
   clk=0;
   forever #5 clk=~clk;

end
initial begin 
    $dumpfile("waves.vcd");
    $dumpvars(0,tb);
    $monitor("time=%0t reset=%b  count=%b",
    $time,reset,count);

    reset=1;
    #10;
    reset=0;
    #150;

    $finish;
end
endmodule

mod_10_counter/waves.vcd
$date
	Mon Jun 22 20:23:20 2026
$end
$version
	Icarus Verilog
$end
$timescale
	1s
$end
$scope module tb $end
$var wire 4 ! count [3:0] $end
$var reg 1 " clk $end
$var reg 1 # reset $end
$scope module dut $end
$var wire 1 " clk $end
$var wire 1 # reset $end
$var reg 4 $ count [3:0] $end
$upscope $end
$upscope $end
$enddefinitions $end
$comment Show the parameter values. $end
$dumpall
$end
#0
$dumpvars
bx $
1#
0"
bx !
$end
#5
b0 !
b0 $
1"
#10
0"
0#
#15
b1 !
b1 $
1"
#20
0"
#25
b10 !
b10 $
1"
#30
0"
#35
b11 !
b11 $
1"
#40
0"
#45
b100 !
b100 $
1"
#50
0"
#55
b101 !
b101 $
1"
#60
0"
#65
b110 !
b110 $
1"
#70
0"
#75
b111 !
b111 $
1"
#80
0"
#85
b1000 !
b1000 $
1"
#90
0"
#95
b1001 !
b1001 $
1"
#100
0"
#105
b0 !
b0 $
1"
#110
0"
#115
b1 !
b1 $
1"
#120
0"
#125
b10 !
b10 $
1"
#130
0"
#135
b11 !
b11 $
1"
#140
0"
#145
b100 !
b100 $
1"
#150
0"
#155
b101 !
b101 $
1"
