jk_flipflop/jkflipflop.sv
module jkflipflop(
    input logic j,
    input logic k,
    input logic clk,
    output logic q
);

always_ff @(posedge clk) begin
    case({j,k})
    2'b00:q<=q;
    2'b01:q<=1'b0;
    2'b10:q<=1'b1;
    2'b11:q<=~q;
    endcase
end 
endmodule

jk_flipflop/tb.sv
module tb;
logic j;
logic k;
logic clk;
logic q;

jkflipflop dut(
    .j(j),
    .k(k),
    .clk(clk),
    .q(q)
);
initial begin 
    clk=0;
    forever #5 clk=~clk;
end
initial begin
    $dumpfile("wave.vcd");
    $dumpvars(0,tb);
    $monitor("t=%0t j=%b k=%b q=%b",
    $time,j,k,q);

    j=0;
    k=0;
    #10;

    j=0;
    k=1;
    #10;

    j=1;
    k=0;
    #10;

    j=1;
    k=1;
    #10;

    j=1;
    k=1;
    #10;

    $finish;
end
endmodule

jk_flipflop/wave.vcd
$date
	Sun Jun 21 04:01:06 2026
$end
$version
	Icarus Verilog
$end
$timescale
	1s
$end
$scope module tb $end
$var wire 1 ! q $end
$var reg 1 " clk $end
$var reg 1 # j $end
$var reg 1 $ k $end
$scope module dut $end
$var wire 1 " clk $end
$var wire 1 # j $end
$var wire 1 $ k $end
$var reg 1 ! q $end
$upscope $end
$upscope $end
$enddefinitions $end
$comment Show the parameter values. $end
$dumpall
$end
#0
$dumpvars
0$
0#
0"
x!
$end
#5
1"
#10
0"
1$
#15
0!
1"
#20
0"
0$
1#
#25
1!
1"
#30
0"
1$
#35
0!
1"
#40
0"
#45
1!
1"
