johnson_counter/counter.sv
module johnson_counter(
    input logic clk,
    input logic reset,
    output logic [3:0]q
);
always_ff @(posedge clk) begin
    if (reset)
        q<=4'b0000;
    else 
        q<={q[2:0],~q[3]};
end
endmodule

johnson_counter/tb.sv
module tb;
logic clk;
logic reset;
logic [3:0] q;

johnson_counter dut(
    .clk(clk),
    .reset(reset),
    .q(q)
);
initial begin 
    clk=0;
    forever #5 clk=~clk;
end
initial begin 
    $dumpfile("waves.vcd");
    $dumpvars(0,tb);
    $monitor("time=%0t reset=%b q=%b",
    $time,reset,q);

    reset=1;
    #10;
    reset=0;
    #200;

    $finish;
end
endmodule

johnson_counter/waves.vcd
$date
	Mon Jun 22 22:10:43 2026
$end
$version
	Icarus Verilog
$end
$timescale
	1s
$end
$scope module tb $end
$var wire 4 ! q [3:0] $end
$var reg 1 " clk $end
$var reg 1 # reset $end
$scope module dut $end
$var wire 1 " clk $end
$var wire 1 # reset $end
$var reg 4 $ q [3:0] $end
$upscope $end
$upscope $end
$enddefinitions $end
$comment Show the parameter values. $end
$dumpall
$end
#0
$dumpvars
bx $
1#
0"
bx !
$end
#5
b0 !
b0 $
1"
#10
0"
0#
#15
b1 !
b1 $
1"
#20
0"
#25
b11 !
b11 $
1"
#30
0"
#35
b111 !
b111 $
1"
#40
0"
#45
b1111 !
b1111 $
1"
#50
0"
#55
b1110 !
b1110 $
1"
#60
0"
#65
b1100 !
b1100 $
1"
#70
0"
#75
b1000 !
b1000 $
1"
#80
0"
#85
b0 !
b0 $
1"
#90
0"
#95
b1 !
b1 $
1"
#100
0"
#105
b11 !
b11 $
1"
#110
0"
#115
b111 !
b111 $
1"
#120
0"
#125
b1111 !
b1111 $
1"
#130
0"
#135
b1110 !
b1110 $
1"
#140
0"
#145
b1100 !
b1100 $
1"
#150
0"
#155
b1000 !
b1000 $
1"
#160
0"
#165
b0 !
b0 $
1"
#170
0"
#175
b1 !
b1 $
1"
#180
0"
#185
b11 !
b11 $
1"
#190
0"
#195
b111 !
b111 $
1"
#200
0"
#205
b1111 !
b1111 $
1"
